mongodatabaseautomation/__init__.py
mongodatabaseautomation/mongo_crud.py
mongoautomation_packagenew-0.0.8.dist-info/LICENSE
mongoautomation_packagenew-0.0.8.dist-info/METADATA
mongoautomation_packagenew-0.0.8.dist-info/WHEEL
mongoautomation_packagenew-0.0.8.dist-info/top_level.txt
mongoautomation_packagenew-0.0.8.dist-info/RECORD
